odoo/addons/shopinvader_lead/README.rst
odoo/addons/shopinvader_lead/__init__.py
odoo/addons/shopinvader_lead/__manifest__.py
odoo/addons/shopinvader_lead/demo/email_demo.xml
odoo/addons/shopinvader_lead/demo/notification_demo.xml
odoo/addons/shopinvader_lead/i18n/shopinvader_lead.pot
odoo/addons/shopinvader_lead/models/__init__.py
odoo/addons/shopinvader_lead/models/lead.py
odoo/addons/shopinvader_lead/models/notification.py
odoo/addons/shopinvader_lead/readme/CONFIGURATION.rst
odoo/addons/shopinvader_lead/readme/CONTRIBUTORS.rst
odoo/addons/shopinvader_lead/readme/CREDITS.rst
odoo/addons/shopinvader_lead/readme/DESCRIPTION.rst
odoo/addons/shopinvader_lead/services/__init__.py
odoo/addons/shopinvader_lead/services/lead.py
odoo/addons/shopinvader_lead/static/description/index.html
odoo/addons/shopinvader_lead/tests/__init__.py
odoo/addons/shopinvader_lead/tests/test_lead.py
odoo14_addon_shopinvader_lead-14.0.1.1.0.dist-info/METADATA
odoo14_addon_shopinvader_lead-14.0.1.1.0.dist-info/WHEEL
odoo14_addon_shopinvader_lead-14.0.1.1.0.dist-info/top_level.txt
odoo14_addon_shopinvader_lead-14.0.1.1.0.dist-info/RECORD
